goblinfish/metrics/trackers.py
goblinfish_metrics_trackers-1.0.5.dist-info/licenses/LICENSE
goblinfish_metrics_trackers-1.0.5.dist-info/METADATA
goblinfish_metrics_trackers-1.0.5.dist-info/WHEEL
goblinfish_metrics_trackers-1.0.5.dist-info/top_level.txt
goblinfish_metrics_trackers-1.0.5.dist-info/RECORD
