Metadata-Version: 2.4
Name: goblinfish-metrics-trackers
Version: 1.0.5
Summary: Context-managed metrics tracking and output, including but not limited to process/subprocess latencies.
Author-email: Brian Allbee <brian.allbee+goblinfish.trackers@gmail.com>
Maintainer-email: Brian Allbee <brian.allbee+goblinfish.trackers@gmail.com>
License: MIT License
Project-URL: Repository, https://bitbucket.org/stonefish-software-studio/goblinfish-metrics-trackers-package
Project-URL: Goblinfish Code Blog Posts, https://goblinfish-code.blogspot.com/search/label/metrics.process_timing
Keywords: aws,cloudwatch,log,metrics,latency,process timing
Classifier: Programming Language :: Python :: 3.13
Classifier: Programming Language :: Python :: 3.12
Classifier: Programming Language :: Python :: 3.11
Classifier: Programming Language :: Python :: 3
Classifier: Development Status :: 5 - Production/Stable
Classifier: Intended Audience :: Developers
Classifier: License :: OSI Approved :: MIT License
Classifier: Natural Language :: English
Classifier: Operating System :: OS Independent
Classifier: Topic :: System :: Logging
Classifier: Topic :: System :: Monitoring
Requires-Python: >=3.11
License-File: LICENSE
Dynamic: license-file
